processing_engine/__init__.py
processing_engine/adapters.py
processing_engine/class_helpers.py
processing_engine/dda_constants.py
processing_engine/dda_models.py
processing_engine/job_service.py
processing_engine/processing_abstract.py
processing_engine/processing_concrete.py
tests/test_adapters.py
tests/test_processing_concrete.py
processing_engine-0.1.17.dist-info/METADATA
processing_engine-0.1.17.dist-info/WHEEL
processing_engine-0.1.17.dist-info/top_level.txt
processing_engine-0.1.17.dist-info/RECORD
