Metadata-Version: 2.1
Name: processing_engine
Version: 0.1.17
Summary: Processing Engine for Data Driven Analytics
Author: Anonym Drifter
License: GNU
Keywords: Processing Engine
Classifier: Development Status :: 3 - Alpha
